django_timestamps/SoftDeleteViewSet.py
django_timestamps/__init__.py
django_timestamps/apps.py
django_timestamps/softDeletion.py
django_timestamps/timestamps.py
django_timestamps-0.0.1.dist-info/LICENSE
django_timestamps-0.0.1.dist-info/METADATA
django_timestamps-0.0.1.dist-info/WHEEL
django_timestamps-0.0.1.dist-info/top_level.txt
django_timestamps-0.0.1.dist-info/RECORD
