Metadata-Version: 2.1
Name: django-timestamps
Version: 0.0.1
Summary: timestamps for django models
Home-page: https://github.com/adrian-cataldo/django-timestamps
Author: Adrian Cataldo
Author-email: adrian.cataldo093@gmail.com
License: UNKNOWN
Platform: UNKNOWN
Classifier: Programming Language :: Python :: 3
Classifier: License :: OSI Approved :: MIT License
Classifier: Operating System :: OS Independent
Requires-Python: >=3.6
